{
  "coverage": "92.1%",
  "expectCount": 76,
  "actualCount": 70,
  "files": {
    "src/model/DeleteRequest.ts": {
      "expectCount": 3,
      "actualCount": 3,
      "undocumentLines": []
    },
    "src/model/GetRequest.ts": {
      "expectCount": 3,
      "actualCount": 3,
      "undocumentLines": []
    },
    "src/model/HTTPRequest.ts": {
      "expectCount": 6,
      "actualCount": 5,
      "undocumentLines": [
        41
      ]
    },
    "src/model/HeadRequest.ts": {
      "expectCount": 3,
      "actualCount": 3,
      "undocumentLines": []
    },
    "src/model/OptionsRequest.ts": {
      "expectCount": 3,
      "actualCount": 3,
      "undocumentLines": []
    },
    "src/model/PatchRequest.ts": {
      "expectCount": 4,
      "actualCount": 4,
      "undocumentLines": []
    },
    "src/model/PostRequest.ts": {
      "expectCount": 4,
      "actualCount": 4,
      "undocumentLines": []
    },
    "src/model/PutRequest.ts": {
      "expectCount": 4,
      "actualCount": 4,
      "undocumentLines": []
    },
    "src/screenplay/abilities/CallAnApi.ts": {
      "expectCount": 13,
      "actualCount": 11,
      "undocumentLines": [
        3,
        4
      ]
    },
    "src/screenplay/interactions/ChangeApiConfig.ts": {
      "expectCount": 16,
      "actualCount": 13,
      "undocumentLines": [
        191,
        238,
        301
      ]
    },
    "src/screenplay/interactions/ChangeApiUrl.ts": {
      "expectCount": 5,
      "actualCount": 5,
      "undocumentLines": []
    },
    "src/screenplay/interactions/Send.ts": {
      "expectCount": 7,
      "actualCount": 7,
      "undocumentLines": []
    },
    "src/screenplay/questions/LastResponse.ts": {
      "expectCount": 5,
      "actualCount": 5,
      "undocumentLines": []
    }
  }
}