{
  "type": "File",
  "start": 0,
  "end": 749,
  "loc": {
    "start": {
      "line": 1,
      "column": 0
    },
    "end": {
      "line": 28,
      "column": 0
    }
  },
  "errors": [],
  "program": {
    "type": "Program",
    "start": 0,
    "end": 749,
    "loc": {
      "start": {
        "line": 1,
        "column": 0
      },
      "end": {
        "line": 28,
        "column": 0
      }
    },
    "sourceType": "module",
    "interpreter": null,
    "body": [
      {
        "type": "ImportDeclaration",
        "start": 0,
        "end": 54,
        "loc": {
          "start": {
            "line": 1,
            "column": 0
          },
          "end": {
            "line": 1,
            "column": 54
          }
        },
        "specifiers": [
          {
            "type": "ImportSpecifier",
            "start": 9,
            "end": 20,
            "loc": {
              "start": {
                "line": 1,
                "column": 9
              },
              "end": {
                "line": 1,
                "column": 20
              }
            },
            "imported": {
              "type": "Identifier",
              "start": 9,
              "end": 20,
              "loc": {
                "start": {
                  "line": 1,
                  "column": 9
                },
                "end": {
                  "line": 1,
                  "column": 20
                },
                "identifierName": "Expectation"
              },
              "name": "Expectation"
            },
            "local": {
              "type": "Identifier",
              "start": 9,
              "end": 20,
              "loc": {
                "start": {
                  "line": 1,
                  "column": 9
                },
                "end": {
                  "line": 1,
                  "column": 20
                },
                "identifierName": "Expectation"
              },
              "name": "Expectation"
            }
          }
        ],
        "source": {
          "type": "StringLiteral",
          "start": 28,
          "end": 53,
          "loc": {
            "start": {
              "line": 1,
              "column": 28
            },
            "end": {
              "line": 1,
              "column": 53
            }
          },
          "extra": {
            "rawValue": "@serenity-js/assertions",
            "raw": "'@serenity-js/assertions'"
          },
          "value": "@serenity-js/assertions"
        }
      },
      {
        "type": "ImportDeclaration",
        "start": 55,
        "end": 98,
        "loc": {
          "start": {
            "line": 2,
            "column": 0
          },
          "end": {
            "line": 2,
            "column": 43
          }
        },
        "specifiers": [
          {
            "type": "ImportSpecifier",
            "start": 64,
            "end": 77,
            "loc": {
              "start": {
                "line": 2,
                "column": 9
              },
              "end": {
                "line": 2,
                "column": 22
              }
            },
            "imported": {
              "type": "Identifier",
              "start": 64,
              "end": 77,
              "loc": {
                "start": {
                  "line": 2,
                  "column": 9
                },
                "end": {
                  "line": 2,
                  "column": 22
                },
                "identifierName": "ElementFinder"
              },
              "name": "ElementFinder"
            },
            "local": {
              "type": "Identifier",
              "start": 64,
              "end": 77,
              "loc": {
                "start": {
                  "line": 2,
                  "column": 9
                },
                "end": {
                  "line": 2,
                  "column": 22
                },
                "identifierName": "ElementFinder"
              },
              "name": "ElementFinder"
            }
          }
        ],
        "source": {
          "type": "StringLiteral",
          "start": 85,
          "end": 97,
          "loc": {
            "start": {
              "line": 2,
              "column": 30
            },
            "end": {
              "line": 2,
              "column": 42
            }
          },
          "extra": {
            "rawValue": "protractor",
            "raw": "'protractor'"
          },
          "value": "protractor"
        }
      },
      {
        "type": "ImportDeclaration",
        "start": 99,
        "end": 169,
        "loc": {
          "start": {
            "line": 3,
            "column": 0
          },
          "end": {
            "line": 3,
            "column": 70
          }
        },
        "specifiers": [
          {
            "type": "ImportSpecifier",
            "start": 108,
            "end": 132,
            "loc": {
              "start": {
                "line": 3,
                "column": 9
              },
              "end": {
                "line": 3,
                "column": 33
              }
            },
            "imported": {
              "type": "Identifier",
              "start": 108,
              "end": 132,
              "loc": {
                "start": {
                  "line": 3,
                  "column": 9
                },
                "end": {
                  "line": 3,
                  "column": 33
                },
                "identifierName": "ElementFinderExpectation"
              },
              "name": "ElementFinderExpectation"
            },
            "local": {
              "type": "Identifier",
              "start": 108,
              "end": 132,
              "loc": {
                "start": {
                  "line": 3,
                  "column": 9
                },
                "end": {
                  "line": 3,
                  "column": 33
                },
                "identifierName": "ElementFinderExpectation"
              },
              "name": "ElementFinderExpectation"
            }
          }
        ],
        "source": {
          "type": "StringLiteral",
          "start": 140,
          "end": 168,
          "loc": {
            "start": {
              "line": 3,
              "column": 41
            },
            "end": {
              "line": 3,
              "column": 69
            }
          },
          "extra": {
            "rawValue": "./ElementFinderExpectation",
            "raw": "'./ElementFinderExpectation'"
          },
          "value": "./ElementFinderExpectation"
        },
        "trailingComments": [
          {
            "type": "CommentBlock",
            "value": "*\n * @desc \n *  \n * @lineNumber \n * 16 \n * @return \n * {Expectation} \n ",
            "start": 170,
            "end": 245,
            "loc": {
              "start": {
                "line": 4,
                "column": 0
              },
              "end": {
                "line": 11,
                "column": 3
              }
            }
          },
          {
            "type": "CommentBlock",
            "value": "*\n * @desc\n *  Expectation that the element is present in the DOM of a page.\n *  Please note that this does not necessarily mean that the element is visible.\n *\n * @returns {Expectation<boolean, ElementFinder>}\n *\n * @see {@link @serenity-js/assertions~Ensure}\n * @see {@link @serenity-js/assertions~Check}\n * @see {@link Wait}\n ",
            "start": 248,
            "end": 581,
            "loc": {
              "start": {
                "line": 14,
                "column": 0
              },
              "end": {
                "line": 24,
                "column": 3
              }
            }
          }
        ]
      },
      {
        "type": "ExportNamedDeclaration",
        "start": 582,
        "end": 748,
        "loc": {
          "start": {
            "line": 25,
            "column": 0
          },
          "end": {
            "line": 27,
            "column": 1
          }
        },
        "specifiers": [],
        "source": null,
        "declaration": {
          "type": "FunctionDeclaration",
          "start": 589,
          "end": 748,
          "loc": {
            "start": {
              "line": 25,
              "column": 7
            },
            "end": {
              "line": 27,
              "column": 1
            }
          },
          "id": {
            "type": "Identifier",
            "start": 598,
            "end": 607,
            "loc": {
              "start": {
                "line": 25,
                "column": 16
              },
              "end": {
                "line": 25,
                "column": 25
              },
              "identifierName": "isPresent"
            },
            "name": "isPresent"
          },
          "generator": false,
          "async": false,
          "params": [],
          "returnType": {
            "type": "TSTypeAnnotation",
            "start": 609,
            "end": 646,
            "loc": {
              "start": {
                "line": 25,
                "column": 27
              },
              "end": {
                "line": 25,
                "column": 64
              }
            },
            "typeAnnotation": {
              "type": "TSTypeReference",
              "start": 611,
              "end": 646,
              "loc": {
                "start": {
                  "line": 25,
                  "column": 29
                },
                "end": {
                  "line": 25,
                  "column": 64
                }
              },
              "typeName": {
                "type": "Identifier",
                "start": 611,
                "end": 622,
                "loc": {
                  "start": {
                    "line": 25,
                    "column": 29
                  },
                  "end": {
                    "line": 25,
                    "column": 40
                  },
                  "identifierName": "Expectation"
                },
                "name": "Expectation"
              },
              "typeParameters": {
                "type": "TSTypeParameterInstantiation",
                "start": 622,
                "end": 646,
                "loc": {
                  "start": {
                    "line": 25,
                    "column": 40
                  },
                  "end": {
                    "line": 25,
                    "column": 64
                  }
                },
                "params": [
                  {
                    "type": "TSBooleanKeyword",
                    "start": 623,
                    "end": 630,
                    "loc": {
                      "start": {
                        "line": 25,
                        "column": 41
                      },
                      "end": {
                        "line": 25,
                        "column": 48
                      }
                    }
                  },
                  {
                    "type": "TSTypeReference",
                    "start": 632,
                    "end": 645,
                    "loc": {
                      "start": {
                        "line": 25,
                        "column": 50
                      },
                      "end": {
                        "line": 25,
                        "column": 63
                      }
                    },
                    "typeName": {
                      "type": "Identifier",
                      "start": 632,
                      "end": 645,
                      "loc": {
                        "start": {
                          "line": 25,
                          "column": 50
                        },
                        "end": {
                          "line": 25,
                          "column": 63
                        },
                        "identifierName": "ElementFinder"
                      },
                      "name": "ElementFinder"
                    }
                  }
                ]
              }
            }
          },
          "body": {
            "type": "BlockStatement",
            "start": 647,
            "end": 748,
            "loc": {
              "start": {
                "line": 25,
                "column": 65
              },
              "end": {
                "line": 27,
                "column": 1
              }
            },
            "body": [
              {
                "type": "ReturnStatement",
                "start": 653,
                "end": 746,
                "loc": {
                  "start": {
                    "line": 26,
                    "column": 4
                  },
                  "end": {
                    "line": 26,
                    "column": 97
                  }
                },
                "argument": {
                  "type": "CallExpression",
                  "start": 660,
                  "end": 745,
                  "loc": {
                    "start": {
                      "line": 26,
                      "column": 11
                    },
                    "end": {
                      "line": 26,
                      "column": 96
                    }
                  },
                  "callee": {
                    "type": "MemberExpression",
                    "start": 660,
                    "end": 697,
                    "loc": {
                      "start": {
                        "line": 26,
                        "column": 11
                      },
                      "end": {
                        "line": 26,
                        "column": 48
                      }
                    },
                    "object": {
                      "type": "Identifier",
                      "start": 660,
                      "end": 684,
                      "loc": {
                        "start": {
                          "line": 26,
                          "column": 11
                        },
                        "end": {
                          "line": 26,
                          "column": 35
                        },
                        "identifierName": "ElementFinderExpectation"
                      },
                      "name": "ElementFinderExpectation"
                    },
                    "property": {
                      "type": "Identifier",
                      "start": 685,
                      "end": 697,
                      "loc": {
                        "start": {
                          "line": 26,
                          "column": 36
                        },
                        "end": {
                          "line": 26,
                          "column": 48
                        },
                        "identifierName": "forElementTo"
                      },
                      "name": "forElementTo"
                    },
                    "computed": false
                  },
                  "arguments": [
                    {
                      "type": "StringLiteral",
                      "start": 698,
                      "end": 714,
                      "loc": {
                        "start": {
                          "line": 26,
                          "column": 49
                        },
                        "end": {
                          "line": 26,
                          "column": 65
                        }
                      },
                      "extra": {
                        "rawValue": "become present",
                        "raw": "'become present'"
                      },
                      "value": "become present"
                    },
                    {
                      "type": "ArrowFunctionExpression",
                      "start": 716,
                      "end": 744,
                      "loc": {
                        "start": {
                          "line": 26,
                          "column": 67
                        },
                        "end": {
                          "line": 26,
                          "column": 95
                        }
                      },
                      "id": null,
                      "generator": false,
                      "async": false,
                      "params": [
                        {
                          "type": "Identifier",
                          "start": 716,
                          "end": 722,
                          "loc": {
                            "start": {
                              "line": 26,
                              "column": 67
                            },
                            "end": {
                              "line": 26,
                              "column": 73
                            },
                            "identifierName": "actual"
                          },
                          "name": "actual"
                        }
                      ],
                      "body": {
                        "type": "CallExpression",
                        "start": 726,
                        "end": 744,
                        "loc": {
                          "start": {
                            "line": 26,
                            "column": 77
                          },
                          "end": {
                            "line": 26,
                            "column": 95
                          }
                        },
                        "callee": {
                          "type": "MemberExpression",
                          "start": 726,
                          "end": 742,
                          "loc": {
                            "start": {
                              "line": 26,
                              "column": 77
                            },
                            "end": {
                              "line": 26,
                              "column": 93
                            }
                          },
                          "object": {
                            "type": "Identifier",
                            "start": 726,
                            "end": 732,
                            "loc": {
                              "start": {
                                "line": 26,
                                "column": 77
                              },
                              "end": {
                                "line": 26,
                                "column": 83
                              },
                              "identifierName": "actual"
                            },
                            "name": "actual"
                          },
                          "property": {
                            "type": "Identifier",
                            "start": 733,
                            "end": 742,
                            "loc": {
                              "start": {
                                "line": 26,
                                "column": 84
                              },
                              "end": {
                                "line": 26,
                                "column": 93
                              },
                              "identifierName": "isPresent"
                            },
                            "name": "isPresent"
                          },
                          "computed": false
                        },
                        "arguments": []
                      }
                    }
                  ]
                }
              }
            ],
            "directives": []
          },
          "leadingComments": [
            {
              "type": "CommentBlock",
              "value": "*\n * @desc \n *  \n * @lineNumber \n * 16 \n * @return \n * {Expectation} \n ",
              "start": 170,
              "end": 245,
              "loc": {
                "start": {
                  "line": 4,
                  "column": 0
                },
                "end": {
                  "line": 11,
                  "column": 3
                }
              }
            },
            {
              "type": "CommentBlock",
              "value": "*\n * @desc\n *  Expectation that the element is present in the DOM of a page.\n *  Please note that this does not necessarily mean that the element is visible.\n *\n * @returns {Expectation<boolean, ElementFinder>}\n *\n * @see {@link @serenity-js/assertions~Ensure}\n * @see {@link @serenity-js/assertions~Check}\n * @see {@link Wait}\n ",
              "start": 248,
              "end": 581,
              "loc": {
                "start": {
                  "line": 14,
                  "column": 0
                },
                "end": {
                  "line": 24,
                  "column": 3
                }
              }
            }
          ],
          "trailingComments": []
        },
        "leadingComments": [
          {
            "type": "CommentBlock",
            "value": "*\n * @desc \n *  \n * @lineNumber \n * 16 \n * @return \n * {Expectation} \n ",
            "start": 170,
            "end": 245,
            "loc": {
              "start": {
                "line": 4,
                "column": 0
              },
              "end": {
                "line": 11,
                "column": 3
              }
            }
          },
          {
            "type": "CommentBlock",
            "value": "*\n * @desc\n *  Expectation that the element is present in the DOM of a page.\n *  Please note that this does not necessarily mean that the element is visible.\n *\n * @returns {Expectation<boolean, ElementFinder>}\n *\n * @see {@link @serenity-js/assertions~Ensure}\n * @see {@link @serenity-js/assertions~Check}\n * @see {@link Wait}\n ",
            "start": 248,
            "end": 581,
            "loc": {
              "start": {
                "line": 14,
                "column": 0
              },
              "end": {
                "line": 24,
                "column": 3
              }
            }
          }
        ]
      }
    ],
    "directives": []
  },
  "comments": [
    {
      "type": "CommentBlock",
      "value": "*\n * @desc \n *  \n * @lineNumber \n * 16 \n * @return \n * {Expectation} \n ",
      "start": 170,
      "end": 245,
      "loc": {
        "start": {
          "line": 4,
          "column": 0
        },
        "end": {
          "line": 11,
          "column": 3
        }
      }
    },
    {
      "type": "CommentBlock",
      "value": "*\n * @desc\n *  Expectation that the element is present in the DOM of a page.\n *  Please note that this does not necessarily mean that the element is visible.\n *\n * @returns {Expectation<boolean, ElementFinder>}\n *\n * @see {@link @serenity-js/assertions~Ensure}\n * @see {@link @serenity-js/assertions~Check}\n * @see {@link Wait}\n ",
      "start": 248,
      "end": 581,
      "loc": {
        "start": {
          "line": 14,
          "column": 0
        },
        "end": {
          "line": 24,
          "column": 3
        }
      }
    }
  ]
}